dialogues/__init__.py
dialogues/main.py
dialogues/utils.py
dialogues/bitod/__init__.py
dialogues/bitod/main.py
dialogues/bitod/src/__init__.py
dialogues/bitod/src/preprocess.py
dialogues/bitod/src/knowledgebase/__init__.py
dialogues/bitod/src/knowledgebase/api.py
dialogues/bitod/src/knowledgebase/en_fa_mappings.py
dialogues/bitod/src/knowledgebase/en_zh_mappings.py
dialogues/bitod/src/knowledgebase/hk_mtr.py
dialogues/bitod/src/knowledgebase/apis/HKMTR_en.json
dialogues/bitod/src/knowledgebase/apis/HKMTR_zh.json
dialogues/bitod/src/knowledgebase/apis/attractions_en_US_search.json
dialogues/bitod/src/knowledgebase/apis/attractions_zh_CN_search.json
dialogues/bitod/src/knowledgebase/apis/hotels_en_US_booking.json
dialogues/bitod/src/knowledgebase/apis/hotels_en_US_search.json
dialogues/bitod/src/knowledgebase/apis/hotels_zh_CN_booking.json
dialogues/bitod/src/knowledgebase/apis/hotels_zh_CN_search.json
dialogues/bitod/src/knowledgebase/apis/restaurants_en_US_booking.json
dialogues/bitod/src/knowledgebase/apis/restaurants_en_US_search.json
dialogues/bitod/src/knowledgebase/apis/restaurants_zh_CN_booking.json
dialogues/bitod/src/knowledgebase/apis/restaurants_zh_CN_search.json
dialogues/bitod/src/knowledgebase/apis/weathers_en_US_search.json
dialogues/bitod/src/knowledgebase/apis/weathers_zh_CN_search.json
dialogues/bitod/src/knowledgebase/mappings/dict_en_zh.json
dialogues/bitod/src/knowledgebase/mappings/en2zh_missing.json
dialogues/bitod/src/knowledgebase/mappings/en_entity_map.json
dialogues/bitod/src/knowledgebase/mappings/hongkong-mtr_with_eng.dot
dialogues/bitod/src/knowledgebase/mappings/mtr_mapping.json
dialogues/bitod/src/knowledgebase/mappings/zh2en_missing.json
dialogues/bitod/src/knowledgebase/mappings/zh_entity_map.json
dialogues/bitod/src/templates/__init__.py
dialogues/bitod/src/templates/generate_neural_response.py
dialogues/bitod/src/templates/generate_template_response.py
dialogues/bitod/src/templates/files/en/human.tsv
dialogues-0.0.3.dist-info/LICENSE
dialogues-0.0.3.dist-info/METADATA
dialogues-0.0.3.dist-info/WHEEL
dialogues-0.0.3.dist-info/entry_points.txt
dialogues-0.0.3.dist-info/top_level.txt
dialogues-0.0.3.dist-info/RECORD
