Metadata-Version: 2.1
Name: dialogues
Version: 0.0.3
Summary: This package provides a unified interface to several dialogue benchmarks
Home-page: https://github.com/Mehrad0711/dialogues
Author: Mehrad Moradshahi
Author-email: mehrad@cs.stanford.edu
License: BSD-3-Clause
Platform: UNKNOWN
